python_package_template/__init__.py
python_package_template/py.typed
python_package_template/template.py
ben_sembira_python_package_template-1.0.0.dist-info/LICENSE
ben_sembira_python_package_template-1.0.0.dist-info/METADATA
ben_sembira_python_package_template-1.0.0.dist-info/WHEEL
ben_sembira_python_package_template-1.0.0.dist-info/top_level.txt
ben_sembira_python_package_template-1.0.0.dist-info/RECORD
